slackron/__init__.py
slackron/config.py
slackron/runner.py
slackron/slack.py
slackron-0.0.9.dist-info/LICENCE
slackron-0.0.9.dist-info/METADATA
slackron-0.0.9.dist-info/WHEEL
slackron-0.0.9.dist-info/entry_points.txt
slackron-0.0.9.dist-info/top_level.txt
slackron-0.0.9.dist-info/RECORD
