Metadata-Version: 2.1
Name: slackron
Version: 0.0.9
Summary: A Python wrapper to notify about cronjob execution to Slack
Home-page: https://github.com/tferreira/slackron
Author: Thomas Ferreira
Author-email: fulura@gmail.com
License: UNKNOWN
Platform: UNKNOWN
Classifier: Programming Language :: Python :: 3
Classifier: License :: OSI Approved :: MIT License
Classifier: Operating System :: OS Independent
Requires-Python: >=3.5
Requires-Dist: PyYAML (==5.1.2)
Requires-Dist: requests (==2.22.0)
Provides-Extra: testing
Requires-Dist: pylint (==2.4.1) ; extra == 'testing'
